tiledbarray/TileDBArraySeed.py
tiledbarray/__init__.py
tiledbarray-0.2.0.dist-info/LICENSE.txt
tiledbarray-0.2.0.dist-info/METADATA
tiledbarray-0.2.0.dist-info/WHEEL
tiledbarray-0.2.0.dist-info/top_level.txt
tiledbarray-0.2.0.dist-info/RECORD
