Metadata-Version: 2.1
Name: tiledbarray
Version: 0.2.0
Summary: TileDb backed objects for array and matrix like data
Home-page: https://github.com/biocpy/tiledbarray/
Author: Jayaram Kancherla
Author-email: jayaram.kancherla@gmail.com
License: MIT
Project-URL: Documentation, https://github.com/biocpy/tiledbarray/
Platform: any
Classifier: Development Status :: 4 - Beta
Classifier: Programming Language :: Python
Requires-Python: >=3.9
License-File: LICENSE.txt
Requires-Dist: importlib-metadata; python_version < "3.8"
Requires-Dist: delayedarray>=0.4.0
Requires-Dist: tiledb
Requires-Dist: numpy
Provides-Extra: testing
Requires-Dist: setuptools; extra == "testing"
Requires-Dist: pytest; extra == "testing"
Requires-Dist: pytest-cov; extra == "testing"
Requires-Dist: scipy; extra == "testing"
